vo_models/__init__.py
vo_models/py.typed
vo_models/adql/__init__.py
vo_models/adql/misc.py
vo_models/registry_interfaces/__init__.py
vo_models/registry_interfaces/models.py
vo_models/stc/__init__.py
vo_models/stc/models.py
vo_models/tapregext/__init__.py
vo_models/tapregext/models.py
vo_models/uws/__init__.py
vo_models/uws/models.py
vo_models/uws/types.py
vo_models/vodataservice/__init__.py
vo_models/vodataservice/models.py
vo_models/voregistry/__init__.py
vo_models/voregistry/models.py
vo_models/voregistry/types.py
vo_models/voresource/__init__.py
vo_models/voresource/models.py
vo_models/voresource/types.py
vo_models/vosi/__init__.py
vo_models/vosi/availability/__init__.py
vo_models/vosi/availability/models.py
vo_models/vosi/capabilities/__init__.py
vo_models/vosi/capabilities/models.py
vo_models/vosi/tables/__init__.py
vo_models/vosi/tables/models.py
vo_models/xlink/__init__.py
vo_models/xlink/xlink.py
vo_models-0.5.1.dist-info/licenses/LICENSE
vo_models-0.5.1.dist-info/METADATA
vo_models-0.5.1.dist-info/WHEEL
vo_models-0.5.1.dist-info/top_level.txt
vo_models-0.5.1.dist-info/RECORD
