Metadata-Version: 2.4
Name: vo-models
Version: 0.5.1
Summary: Pydantic data models for IVOA protocols
Author-email: Joshua Fraustro <jfraustro@stsci.edu>, MAST Archive Developers <archive@stsci.edu>
Project-URL: Homepage, https://github.com/spacetelescope/vo-models
Project-URL: Issues, https://github.com/spacetelescope/vo-models/issues
Keywords: ivoa,pydantic,pydantic-xml
Classifier: Topic :: Scientific/Engineering :: Astronomy
Classifier: Topic :: Software Development :: Libraries :: Python Modules
Classifier: License :: OSI Approved :: MIT License
Requires-Python: >=3.10
License-File: LICENSE
Requires-Dist: pydantic>2
Requires-Dist: pydantic-xml[lxml]>=2.6.0
Provides-Extra: test
Requires-Dist: pytest; extra == "test"
Requires-Dist: pytest-cov; extra == "test"
Provides-Extra: dev
Requires-Dist: pylint; extra == "dev"
Requires-Dist: ruff; extra == "dev"
Requires-Dist: pre-commit; extra == "dev"
Provides-Extra: docs
Requires-Dist: sphinx; extra == "docs"
Requires-Dist: sphinx_design; extra == "docs"
Requires-Dist: furo; extra == "docs"
Requires-Dist: sphinx-copybutton; extra == "docs"
Requires-Dist: toml; extra == "docs"
Requires-Dist: sphinx_autodoc_typehints; extra == "docs"
Dynamic: license-file
